wdisp/__init__.py
wdisp/__main__.py
wdisp/app.py
wdisp/config.py
wdisp/display.py
wdisp/server.py
wdisp/service.py
wdisp/wwwroot/3rdpartylicenses.txt
wdisp/wwwroot/favicon.ico
wdisp/wwwroot/index.html
wdisp/wwwroot/inline.318b50c57b4eba3d437b.bundle.js
wdisp/wwwroot/main.41a3477e8db79b7b1b47.bundle.js
wdisp/wwwroot/main.ec25aa28db2b94db8ea0.bundle.js
wdisp/wwwroot/main.fe607a4484b8632f96d6.bundle.js
wdisp/wwwroot/polyfills.b6b2cd0d4c472ac3ac12.bundle.js
wdisp/wwwroot/styles.12a7285df31d4dd5697d.bundle.css
wdisp-1.0.1.dist-info/DESCRIPTION.rst
wdisp-1.0.1.dist-info/METADATA
wdisp-1.0.1.dist-info/RECORD
wdisp-1.0.1.dist-info/WHEEL
wdisp-1.0.1.dist-info/metadata.json
wdisp-1.0.1.dist-info/top_level.txt
